LICENSE
MANIFEST.in
README.md
requirements.txt
setup.py
cp2mqtt/__init__.py
cp2mqtt/__main__.py
cp2mqtt/config.py
cp2mqtt.egg-info/PKG-INFO
cp2mqtt.egg-info/SOURCES.txt
cp2mqtt.egg-info/dependency_links.txt
cp2mqtt.egg-info/entry_points.txt
cp2mqtt.egg-info/requires.txt
cp2mqtt.egg-info/top_level.txt